monk_gluoncv_finetune_test/__init__.py
monk_gluoncv_finetune_test/detector_prototype.py
monk_gluoncv_finetune_test/im2rec.py
monk_gluoncv_finetune_test/inference_prototype.py
monk_obj_test1-0.0.1.dist-info/LICENSE.md
monk_obj_test1-0.0.1.dist-info/METADATA
monk_obj_test1-0.0.1.dist-info/WHEEL
monk_obj_test1-0.0.1.dist-info/dependency_links.txt
monk_obj_test1-0.0.1.dist-info/top_level.txt
monk_obj_test1-0.0.1.dist-info/RECORD
