Metadata-Version: 2.1
Name: monk-obj-test1
Version: 0.0.1
Summary: Monk Object Detection's 1_gluoncv_finetune
Home-page: https://github.com/Tessellate-Imaging/Monk_Object_Detection
Author: Tessellate Imaging
Author-email: abhishek@tessellateimaging.com
License: UNKNOWN
Platform: UNKNOWN
Classifier: Programming Language :: Python :: 3
Classifier: License :: OSI Approved :: Apache Software License
Classifier: Operating System :: OS Independent
Classifier: Environment :: GPU :: NVIDIA CUDA :: 9.0
Requires-Python: >=3.6
Requires-Dist: numpy
Requires-Dist: scipy
Requires-Dist: tqdm
Requires-Dist: pillow
Requires-Dist: opencv-python
Requires-Dist: cython
Requires-Dist: jupyter
Requires-Dist: notebook
Requires-Dist: pandas
Requires-Dist: matplotlib
Requires-Dist: xmltodict
Requires-Dist: mxnet-cu90
Requires-Dist: gluoncv
